pywet/__init__.py
pywet-0.1.4.dist-info/METADATA
pywet-0.1.4.dist-info/WHEEL
pywet-0.1.4.dist-info/entry_points.txt
pywet-0.1.4.dist-info/licenses/LICENSE
pywet-0.1.4.dist-info/RECORD
