Metadata-Version: 2.4
Name: pywet
Version: 0.1.4
Summary: Python Windows Emergency Tiler - a workflow centric windows tiling manager for Windows
Author-email: tonyatpeking <tonyatpeking@gmail.com>
License: MIT-Permissive-AI License
License-File: LICENSE
Requires-Python: >=3.12
Requires-Dist: pywin32; sys_platform == 'win32'
